bukalapak_lazada_price_scrapper/__init__.py
bukalapak_lazada_price_scrapper/scraper.py
bukalapak_lazada_price_scrapper-0.2.2.dist-info/LICENSE.md
bukalapak_lazada_price_scrapper-0.2.2.dist-info/METADATA
bukalapak_lazada_price_scrapper-0.2.2.dist-info/WHEEL
bukalapak_lazada_price_scrapper-0.2.2.dist-info/top_level.txt
bukalapak_lazada_price_scrapper-0.2.2.dist-info/RECORD
