Metadata-Version: 2.1
Name: bukalapak-lazada-price-scrapper
Version: 0.2.2
Summary: A package for scraping product prices from Bukalapak and Lazada.
Home-page: https://github.com/RichardOwen2/bukalapak-lazada-price-scrapper
Author: Richard Owen Hoan
Author-email: richardowen2411@gmail.com
Classifier: Programming Language :: Python :: 3
Classifier: License :: OSI Approved :: MIT License
Classifier: Operating System :: OS Independent
Requires-Python: >=3.6
License-File: LICENSE.md
Requires-Dist: selenium
Requires-Dist: webdriver-manager
Requires-Dist: beautifulsoup4
Requires-Dist: requests
